flexver.py
flexver-1.1.1.dist-info/LICENSE
flexver-1.1.1.dist-info/METADATA
flexver-1.1.1.dist-info/WHEEL
flexver-1.1.1.dist-info/RECORD
