Metadata-Version: 2.1
Name: flexver
Version: 1.1.1
Summary: FlexVer is a SemVer-compatible intuitive comparator for free-form versioning strings as seen in the wild.
Home-page: https://github.com/unascribed/FlexVer
License: CC0-1.0
Author: ENDERZOMBI102
Author-email: enderzombi102.end@gmail.com
Requires-Python: >=3.8,<4.0
Classifier: License :: CC0 1.0 Universal (CC0 1.0) Public Domain Dedication
Classifier: Programming Language :: Python :: 3
Classifier: Programming Language :: Python :: 3.8
Classifier: Programming Language :: Python :: 3.9
Classifier: Programming Language :: Python :: 3.10
Classifier: Programming Language :: Python :: 3.11
Classifier: Topic :: Software Development :: Libraries :: Python Modules
Project-URL: Repository, https://github.com/unascribed/FlexVer
